citextract/__init__.py
citextract/models/__init__.py
citextract/models/refxtract.py
citextract/models/titlextract.py
citextract/utils/__init__.py
citextract/utils/model.py
citextract/utils/pdf.py
tests/__init__.py
tests/test_pdf_utils.py
tests/utils.py
citextract-0.0.4.dist-info/LICENSE
citextract-0.0.4.dist-info/METADATA
citextract-0.0.4.dist-info/WHEEL
citextract-0.0.4.dist-info/top_level.txt
citextract-0.0.4.dist-info/RECORD
