Metadata-Version: 2.1
Name: citextract
Version: 0.0.4
Summary: CiteXtract - Bringing structure to the papers on ArXiv.
Home-page: https://www.citextract.com/
Author: Kevin Jacobs
Author-email: kevin91nl@gmail.com
License: UNKNOWN
Platform: UNKNOWN
Classifier: Programming Language :: Python :: 3
Classifier: License :: OSI Approved :: MIT License
Classifier: Operating System :: OS Independent
